setup.py
WikiPy/__init__.py
WikiPy/__main__.py
WikiPy.egg-info/PKG-INFO
WikiPy.egg-info/SOURCES.txt
WikiPy.egg-info/dependency_links.txt
WikiPy.egg-info/not-zip-safe
WikiPy.egg-info/top_level.txt