Metadata-Version: 1.0
Name: WikiPy
Version: 1.16
Summary: Send emails and convert markdown files to PDFs with pandoc from WikiPy.
Home-page: https://github.com/TommyArnzen1/WikiPyEmail
Author: WikiPy
Author-email: arnzent1@mymail.nku.edu
License: MIT
Platform: UNKNOWN
